[
  {
    "name": "AIR FRYER 3.0 LTR. 800 WATT.",
    "brand": "OCEAN ELECTRIC",
    "sku": "OAF506",
    "quantity": 2507,
    "price": "4775"
  },
  {
    "name": "AIR FRYER 4.0 LTR. 1500 WATT. DIGITAL W/SAFETY LOCK",
    "brand": "OCEAN ELECTRIC",
    "sku": "OAF8004D",
    "quantity": 929,
    "price": "6450"
  },
  {
    "name": "AIR FRYER 4.0 LTR. 1500 WATT. W/SAFETY LOCK",
    "brand": "OCEAN ELECTRIC",
    "sku": "OAF8004",
    "quantity": 866,
    "price": "5950"
  },
  {
    "name": "AIR FRYER 5.0 LTR. 1500 WATT.",
    "brand": "OCEAN ELECTRIC",
    "sku": "OAF8045",
    "quantity": 821,
    "price": "6650"
  },
  {
    "name": "AIR FRYER 5.0 LTR. 1500 WATT. DIGITAL",
    "brand": "OCEAN ELECTRIC",
    "sku": "OAF8045D",
    "quantity": 817,
    "price": "7350"
  },
  {
    "name": "BLENDER OCEAN (3 IN 1) 750W RED INDIAN",
    "brand": "OCEAN ELECTRIC",
    "sku": "OMGV22R",
    "quantity": 2187,
    "price": "4475"
  },
  {
    "name": "COFFEE MAKER 1.5 LTR",
    "brand": "OCEAN ELECTRIC",
    "sku": "OCM6622",
    "quantity": 2187,
    "price": "3550"
  },
  {
    "name": "GAS COOKER DOUBLE BURNER",
    "brand": "OCEAN ELECTRIC",
    "sku": "OGC230B",
    "quantity": 1951,
    "price": "8750"
  },
  {
    "name": "HAND MIXER 4 STICK PINK COLOR",
    "brand": "OCEAN ELECTRIC",
    "sku": "OHM736",
    "quantity": 1808,
    "price": "1775"
  },
  {
    "name": "HAND MIXER WHITE COLOR",
    "brand": "OCEAN ELECTRIC",
    "sku": "OHM751",
    "quantity": 1666,
    "price": "1475"
  },
  {
    "name": "HAND MIXER WITH CONTAINER 300W",
    "brand": "OCEAN ELECTRIC",
    "sku": "OSM8006N",
    "quantity": 745,
    "price": "3775"
  },
  {
    "name": "INFRARED COOKER OCEAN BLUE 2000 WATT",
    "brand": "OCEAN ELECTRIC",
    "sku": "OIC71",
    "quantity": 2938,
    "price": "4450"
  },
  {
    "name": "IRON DRY CERAMIC SOLEPLATE BLUE",
    "brand": "OCEAN ELECTRIC",
    "sku": "ODI2BLC",
    "quantity": 2942,
    "price": "1350"
  },
  {
    "name": "KETTLE ELECTRIC 1.0 LTR.",
    "brand": "OCEAN ELECTRIC",
    "sku": "OEK1001",
    "quantity": 1646,
    "price": "1250"
  },
  {
    "name": "KETTLE ELECTRIC 1.5 LTR.",
    "brand": "OCEAN ELECTRIC",
    "sku": "OEK1519",
    "quantity": 967,
    "price": "1550"
  },
  {
    "name": "KETTLE ELECTRIC 1.5 LTR.",
    "brand": "OCEAN ELECTRIC",
    "sku": "OEK8720",
    "quantity": 1777,
    "price": "1750"
  },
  {
    "name": "KETTLE ELECTRIC 1.7 LTR.",
    "brand": "OCEAN ELECTRIC",
    "sku": "OEK1792",
    "quantity": 375,
    "price": "1350"
  },
  {
    "name": "KETTLE ELECTRIC 1.7 LTR. BLACK",
    "brand": "OCEAN ELECTRIC",
    "sku": "OEK8722B",
    "quantity": 707,
    "price": "1650"
  },
  {
    "name": "KETTLE ELECTRIC 1.7 LTR. WHITE",
    "brand": "OCEAN ELECTRIC",
    "sku": "OEK8722W",
    "quantity": 750,
    "price": "1650"
  },
  {
    "name": "KETTLE ELECTRIC 1.7 LTR. WHITE COLOR",
    "brand": "OCEAN ELECTRIC",
    "sku": "OEK8312",
    "quantity": 1315,
    "price": "1275"
  },
  {
    "name": "KETTLE ELECTRIC 1.8 LTR.",
    "brand": "OCEAN ELECTRIC",
    "sku": "OEK5019",
    "quantity": 2378,
    "price": "1700"
  },
  {
    "name": "KETTLE ELECTRIC 1.8 LTR. S/S",
    "brand": "OCEAN ELECTRIC",
    "sku": "OEKA9",
    "quantity": 2919,
    "price": "795"
  },
  {
    "name": "MEAT GRINDER 1600W",
    "brand": "OCEAN ELECTRIC",
    "sku": "OMG3250R",
    "quantity": 643,
    "price": "7540"
  },
  {
    "name": "MULTI COOKER FAST 1.6 LTR. 600W",
    "brand": "OCEAN ELECTRIC",
    "sku": "OFMC18C",
    "quantity": 389,
    "price": "3575"
  },
  {
    "name": "OVEN ELECTRIC 20 LTR. WITH CONVECTION",
    "brand": "OCEAN ELECTRIC",
    "sku": "OEO32012C",
    "quantity": 244,
    "price": "5950"
  },
  {
    "name": "OVEN MICROWAVE 20 LTR. MACHANICAL",
    "brand": "OCEAN ELECTRIC",
    "sku": "OMOP70T20LV1E",
    "quantity": 316,
    "price": "7975"
  },
  {
    "name": "RICE COOKER 1.2 LTR. 500W",
    "brand": "OCEAN ELECTRIC",
    "sku": "ORC12GA",
    "quantity": 446,
    "price": "3375"
  },
  {
    "name": "RICE COOKER 1.8 LTR. 700W",
    "brand": "OCEAN ELECTRIC",
    "sku": "ORC18GA",
    "quantity": 737,
    "price": "3975"
  },
  {
    "name": "RICE COOKER 2.2 LTR. 900W",
    "brand": "OCEAN ELECTRIC",
    "sku": "ORC22GA",
    "quantity": 741,
    "price": "4475"
  },
  {
    "name": "RICE COOKER 2.8 LTR. 1000W",
    "brand": "OCEAN ELECTRIC",
    "sku": "ORC28GA",
    "quantity": 1239,
    "price": "4875"
  },
  {
    "name": "SANDWICH MAKER 2 SLICE",
    "brand": "OCEAN ELECTRIC",
    "sku": "OSM226",
    "quantity": 1091,
    "price": "1650"
  },
  {
    "name": "SANDWICH MAKER 700W",
    "brand": "OCEAN ELECTRIC",
    "sku": "OSM233",
    "quantity": 357,
    "price": "1575"
  },
  {
    "name": "SANDWICH MAKER FOR MULTIPURPOSE 750W BLACK",
    "brand": "OCEAN ELECTRIC",
    "sku": "OSMC023B",
    "quantity": 284,
    "price": "1475"
  },
  {
    "name": "SANDWICH MAKER FOR MULTIPURPOSE 750W WHITE",
    "brand": "OCEAN ELECTRIC",
    "sku": "OSMC023W",
    "quantity": 3446,
    "price": "1475"
  },
  {
    "name": "SANDWICH MAKER WOODEN HANDLE",
    "brand": "OCEAN ELECTRIC",
    "sku": "OSM1F56",
    "quantity": 361,
    "price": "2175"
  },
  {
    "name": "TOASTER BREAD 2 SLICE BLACK WITH COVER",
    "brand": "OCEAN ELECTRIC",
    "sku": "OBT802B",
    "quantity": 1018,
    "price": "1495"
  },
  {
    "name": "YOGURT MAKER WITH PORTABLE CUP",
    "brand": "OCEAN ELECTRIC",
    "sku": "OYM2JA",
    "quantity": 669,
    "price": "1875"
  },
  {
    "name": "BOWL MIXING 0.5 LTR. (14X8) CM",
    "brand": "OCUISINE",
    "sku": "178BC00",
    "quantity": 384,
    "price": "775"
  },
  {
    "name": "BOWL MIXING 1.0 LTR. (17X10) CM",
    "brand": "OCUISINE",
    "sku": "179BC00",
    "quantity": 385,
    "price": "875"
  },
  {
    "name": "BOWL MIXING 2.0 LTR. (21X11) CM",
    "brand": "OCUISINE",
    "sku": "180BC00",
    "quantity": 402,
    "price": "1075"
  },
  {
    "name": "BOWL MIXING 3.0 LTR. (24X13) CM",
    "brand": "OCUISINE",
    "sku": "181BC00",
    "quantity": 402,
    "price": "1375"
  },
  {
    "name": "DISH LOAF 28.0\"",
    "brand": "OCUISINE",
    "sku": "835BC00",
    "quantity": 282,
    "price": "1175"
  },
  {
    "name": "FLAN DISH (27X27) CM",
    "brand": "OCUISINE",
    "sku": "803BC00",
    "quantity": 392,
    "price": "1250"
  },
  {
    "name": "FLUTTED FLAN DISH (26X26) CM",
    "brand": "OCUISINE",
    "sku": "818BC00",
    "quantity": 402,
    "price": "1250"
  },
  {
    "name": "ROASTER RECT. W/PLASTIC LID (36.3X22.3X8.14)CM",
    "brand": "OCUISINE",
    "sku": "2009302",
    "quantity": 291,
    "price": "1585"
  },
  {
    "name": "ROASTER RECTANGULAR 1.6 LTR. (28X20X5) CM",
    "brand": "OCUISINE",
    "sku": "217BC00",
    "quantity": 1380,
    "price": "1250"
  },
  {
    "name": "ROASTER RECTANGULAR 2.0 LTR. (32X20X5) CM",
    "brand": "OCUISINE",
    "sku": "247BC00",
    "quantity": 679,
    "price": "1350"
  },
  {
    "name": "ROASTER RECTANGULAR 2.6 LTR. (35X22X5) CM",
    "brand": "OCUISINE",
    "sku": "248BC00",
    "quantity": 780,
    "price": "1550"
  },
  {
    "name": "ROASTER RECTANGULAR 3.6 LTR. (39X24X6) CM",
    "brand": "OCUISINE",
    "sku": "249BC00",
    "quantity": 540,
    "price": "1850"
  },
  {
    "name": "ROASTER RECTANGULAR 4.5 LTR. (40X27X7) CM",
    "brand": "OCUISINE",
    "sku": "240BC00",
    "quantity": 540,
    "price": "2250"
  },
  {
    "name": "ROASTER RECTANGULAR W/LID (23X15X6) CM",
    "brand": "OCUISINE",
    "sku": "215PC00",
    "quantity": 1368,
    "price": "1175"
  },
  {
    "name": "ROASTER RECTANGULAR W/LID (28X20X6) CM",
    "brand": "OCUISINE",
    "sku": "216PC00",
    "quantity": 970,
    "price": "1575"
  },
  {
    "name": "ROASTER ROUND WITH LID 1.0 LTR",
    "brand": "OCUISINE",
    "sku": "207PC00",
    "quantity": 765,
    "price": "1075"
  },
  {
    "name": "ROASTER SQUARE 1.0 LTR. (20X17X6) CM",
    "brand": "OCUISINE",
    "sku": "211BC00",
    "quantity": 760,
    "price": "975"
  },
  {
    "name": "ROASTER SQUARE 1.6 LTR. (25X22X5) CM",
    "brand": "OCUISINE",
    "sku": "209BC00",
    "quantity": 576,
    "price": "1275"
  },
  {
    "name": "ROASTER SQUARE WITH LID (20X17) CM",
    "brand": "OCUISINE",
    "sku": "211PC00",
    "quantity": 972,
    "price": "1075"
  },
  {
    "name": "ROASTER SQUARE WITH LID (25X22) CM",
    "brand": "OCUISINE",
    "sku": "212PC00",
    "quantity": 970,
    "price": "1475"
  },
  {
    "name": "ROASTER SQUARE WITH LID (25X22X5) CM",
    "brand": "OCUISINE",
    "sku": "209PC00",
    "quantity": 920,
    "price": "1375"
  },
  {
    "name": "BABY SET 3  #",
    "brand": "LUMINARC-CHINA",
    "sku": "Q7282",
    "quantity": 1663,
    "price": "445"
  },
  {
    "name": "CHOPSTICK WOODEN (2  SET)",
    "brand": "LUMINARC-CHINA",
    "sku": "V1160CS",
    "quantity": 329,
    "price": "144"
  },
  {
    "name": "DINNER PLATE FLAT $ 27CM SQUARE",
    "brand": "LUMINARC-CHINA",
    "sku": "Q8944",
    "quantity": 1686,
    "price": "380"
  },
  {
    "name": "DIWALI CURRY BOWL $ 12CM",
    "brand": "LUMINARC-CHINA",
    "sku": "N3600",
    "quantity": 1189,
    "price": "210"
  },
  {
    "name": "DIWALI CURRY BOWL 21 # CM BIG",
    "brand": "LUMINARC-CHINA",
    "sku": "N3602",
    "quantity": 257,
    "price": "550"
  },
  {
    "name": "DIWALI DEEP PLATE 20 CM",
    "brand": "LUMINARC-CHINA",
    "sku": "N3605",
    "quantity": 939,
    "price": "325"
  },
  {
    "name": "DIWALI SAUCE PLATE $ 11CM",
    "brand": "LUMINARC-CHINA",
    "sku": "N3607",
    "quantity": 776,
    "price": "120"
  },
  {
    "name": "LOTUSIA CURRY BOWL 12 # CM",
    "brand": "LUMINARC-CHINA",
    "sku": "Q6573",
    "quantity": 1693,
    "price": "275"
  },
  {
    "name": "LOTUSIA CURRY BOWL 18 # CM MEDIUM",
    "brand": "LUMINARC-CHINA",
    "sku": "N3617",
    "quantity": 283,
    "price": "475"
  },
  {
    "name": "LOTUSIA SALAD BOWL $ 20CM",
    "brand": "LUMINARC-CHINA",
    "sku": "Q9691",
    "quantity": 1647,
    "price": "495"
  },
  {
    "name": "TUMBLER ASTEL 270ML $",
    "brand": "LUMINARC-CHINA",
    "sku": "V4198",
    "quantity": 56408,
    "price": "190"
  },
  {
    "name": "TUMBLER FUNAMBLUE $ DDI 270ML",
    "brand": "LUMINARC-CHINA",
    "sku": "L6534",
    "quantity": 3092,
    "price": "160"
  },
  {
    "name": "TUMBLER HIGHBALL 290ML ISLAND",
    "brand": "LUMINARC-CHINA",
    "sku": "E5880",
    "quantity": 3277,
    "price": "197"
  },
  {
    "name": "VIGNE TUMBLER 220ML $",
    "brand": "LUMINARC-CHINA",
    "sku": "H4517",
    "quantity": 2409,
    "price": "160"
  },
  {
    "name": "WATER JUG SET 5  ELECTRONIC COLOR",
    "brand": "LUMINARC-CHINA",
    "sku": "V1660",
    "quantity": 848,
    "price": "1975"
  },
  {
    "name": "COOLER BOX 10.0 LTR. MARINA",
    "brand": "LION STAR",
    "sku": "116",
    "quantity": 250,
    "price": "4575"
  },
  {
    "name": "COOLER BOX 16.0 LTR. # MARINA",
    "brand": "LION STAR",
    "sku": "117",
    "quantity": 232,
    "price": "6175"
  },
  {
    "name": "COOLER BOX 22.0 LTR. MARINA",
    "brand": "LION STAR",
    "sku": "118",
    "quantity": 284,
    "price": "8275"
  },
  {
    "name": "COOLER BOX 33.0 LTR. MARINA",
    "brand": "LION STAR",
    "sku": "119",
    "quantity": 306,
    "price": "10575"
  },
  {
    "name": "COOLER BOX 5.5 LTR. MARINA",
    "brand": "LION STAR",
    "sku": "115",
    "quantity": 363,
    "price": "2375"
  },
  {
    "name": "WATER JUG 1.3 LTR. THERMO",
    "brand": "LION STAR",
    "sku": "KI",
    "quantity": 335,
    "price": "975"
  },
  {
    "name": "WATER JUG 2.1 LTR. THERMO",
    "brand": "LION STAR",
    "sku": "K12",
    "quantity": 361,
    "price": "1575"
  },
  {
    "name": "COFFEE SPOON",
    "brand": "KITCHEN (Cutlery)",
    "sku": "C002ACS",
    "quantity": 464,
    "price": 125
  },
  {
    "name": "COFFEE SPOON 12.5CM $",
    "brand": "KITCHEN (Cutlery)",
    "sku": "10105CS",
    "quantity": 402,
    "price": 70
  },
  {
    "name": "CULTERY SET 16 PCS",
    "brand": "KITCHEN (Cutlery)",
    "sku": "808216P",
    "quantity": 1657,
    "price": 1545
  },
  {
    "name": "CURRY SPOON",
    "brand": "KITCHEN (Cutlery)",
    "sku": "IHWCSP001",
    "quantity": 1073,
    "price": 145
  },
  {
    "name": "CURRY SPOON",
    "brand": "KITCHEN (Cutlery)",
    "sku": "IHWCSP002",
    "quantity": 1442,
    "price": 145
  },
  {
    "name": "CURRY SPOON",
    "brand": "KITCHEN (Cutlery)",
    "sku": "IHWCSP003",
    "quantity": 1652,
    "price": 145
  },
  {
    "name": "CUTLERY SET 12 PCS",
    "brand": "KITCHEN (Cutlery)",
    "sku": "808212P",
    "quantity": 1854,
    "price": 1045
  },
  {
    "name": "DESSERT KNIFE",
    "brand": "KITCHEN (Cutlery)",
    "sku": "101029DK",
    "quantity": 903,
    "price": 160
  },
  {
    "name": "DESSERT KNIFE",
    "brand": "KITCHEN (Cutlery)",
    "sku": "111729DK",
    "quantity": 380,
    "price": 190
  },
  {
    "name": "DESSERT KNIFE W/OUT LOGO",
    "brand": "KITCHEN (Cutlery)",
    "sku": "101029",
    "quantity": 624,
    "price": 145
  },
  {
    "name": "DINNER FISH FORK",
    "brand": "KITCHEN (Cutlery)",
    "sku": "101021DFF",
    "quantity": 1269,
    "price": 90
  },
  {
    "name": "DINNER FISH FORK",
    "brand": "KITCHEN (Cutlery)",
    "sku": "111721DFK",
    "quantity": 711,
    "price": 100
  },
  {
    "name": "DINNER FORK",
    "brand": "KITCHEN (Cutlery)",
    "sku": "C002ADF",
    "quantity": 355,
    "price": 200
  },
  {
    "name": "DINNER FORK",
    "brand": "KITCHEN (Cutlery)",
    "sku": "ZQ6805DF",
    "quantity": 863,
    "price": 115
  },
  {
    "name": "DINNER FORK O",
    "brand": "KITCHEN (Cutlery)",
    "sku": "W032DF",
    "quantity": 393,
    "price": 100
  },
  {
    "name": "DINNER KNIFE",
    "brand": "KITCHEN (Cutlery)",
    "sku": "ZQ6801DK",
    "quantity": 1317,
    "price": 150
  },
  {
    "name": "DINNER KNIFE **",
    "brand": "KITCHEN (Cutlery)",
    "sku": "22061DK",
    "quantity": 418,
    "price": 100
  },
  {
    "name": "DINNER KNIFE 23 CM []",
    "brand": "KITCHEN (Cutlery)",
    "sku": "1010DK",
    "quantity": 807,
    "price": 50
  },
  {
    "name": "DINNER SPOON",
    "brand": "KITCHEN (Cutlery)",
    "sku": "C002ADS",
    "quantity": 200,
    "price": 200
  },
  {
    "name": "DINNER SPOON",
    "brand": "KITCHEN (Cutlery)",
    "sku": "ZQ6804DS",
    "quantity": 614,
    "price": 115
  },
  {
    "name": "FISH KNIFE",
    "brand": "KITCHEN (Cutlery)",
    "sku": "101028FK",
    "quantity": 1138,
    "price": 125
  },
  {
    "name": "FISH KNIFE",
    "brand": "KITCHEN (Cutlery)",
    "sku": "111728FK",
    "quantity": 1730,
    "price": 135
  },
  {
    "name": "PASTY FORK",
    "brand": "KITCHEN (Cutlery)",
    "sku": "ZQ6809PF",
    "quantity": 324,
    "price": 85
  },
  {
    "name": "SERVING SPOON LONG",
    "brand": "KITCHEN (Cutlery)",
    "sku": "204M",
    "quantity": 1070,
    "price": 345
  },
  {
    "name": "SERVING SPOON LONG",
    "brand": "KITCHEN (Cutlery)",
    "sku": "504M",
    "quantity": 1333,
    "price": 345
  },
  {
    "name": "SERVING SPOON SHORT",
    "brand": "KITCHEN (Cutlery)",
    "sku": "204X",
    "quantity": 1470,
    "price": 295
  },
  {
    "name": "SERVING SPOON SHORT",
    "brand": "KITCHEN (Cutlery)",
    "sku": "504X",
    "quantity": 1499,
    "price": 295
  },
  {
    "name": "SOUP LADLE BIG 27 CM",
    "brand": "KITCHEN (Cutlery)",
    "sku": "111733",
    "quantity": 291,
    "price": 295
  },
  {
    "name": "SOUP SPOON BIG W/OUT LOGO",
    "brand": "KITCHEN (Cutlery)",
    "sku": "10108",
    "quantity": 449,
    "price": 90
  },
  {
    "name": "TABLE DINNER FORK W/OUT LOGO",
    "brand": "KITCHEN (Cutlery)",
    "sku": "101015",
    "quantity": 495,
    "price": 85
  },
  {
    "name": "TABLE DINNER KNIFE",
    "brand": "KITCHEN (Cutlery)",
    "sku": "101025TDK",
    "quantity": 3430,
    "price": 190
  },
  {
    "name": "TABLE DINNER KNIFE W/OUT LOGO",
    "brand": "KITCHEN (Cutlery)",
    "sku": "101025",
    "quantity": 227,
    "price": 175
  },
  {
    "name": "TABLE DINNER SPOON W/OUT LOGO",
    "brand": "KITCHEN (Cutlery)",
    "sku": "10101",
    "quantity": 489,
    "price": 85
  },
  {
    "name": "TEA SPOON",
    "brand": "KITCHEN (Cutlery)",
    "sku": "ZQ6808TS",
    "quantity": 835,
    "price": 95
  },
  {
    "name": "TEA SPOON W/OUT LOGO",
    "brand": "KITCHEN (Cutlery)",
    "sku": "10104",
    "quantity": 496,
    "price": 60
  },
  {
    "name": "FOOD TRAY JAPANES (31X24.5) CM",
    "brand": "KITCHEN(Commercial)",
    "sku": "A960",
    "quantity": 233,
    "price": 1285
  },
  {
    "name": "FOOD TRAY JAPANES (31X24.5) CM",
    "brand": "KITCHEN(Commercial)",
    "sku": "A960E",
    "quantity": 295,
    "price": 1685
  },
  {
    "name": "FOOD WARMER OVAL SHAP (ZEBRA)",
    "brand": "KITCHEN(Commercial)",
    "sku": "192139",
    "quantity": 485,
    "price": 12975
  },
  {
    "name": "BBQ STICK 12 PCS SET",
    "brand": "KITCHEN (Commercial-domestic)",
    "sku": "161793",
    "quantity": 237,
    "price": 195
  },
  {
    "name": "COFFEE GRINDER/ BLENDER",
    "brand": "KITCHEN (Commercial-domestic)",
    "sku": "MS308",
    "quantity": 938,
    "price": 125
  },
  {
    "name": "DISH RACK OPP PACK",
    "brand": "KITCHEN (Commercial-domestic)",
    "sku": "HY929",
    "quantity": 691,
    "price": 945
  },
  {
    "name": "EGG PAN 12CM PINK & BLUE",
    "brand": "KITCHEN (Commercial-domestic)",
    "sku": "1690731",
    "quantity": 263,
    "price": 395
  },
  {
    "name": "EGG PAN 14CM PINK & BLUE",
    "brand": "KITCHEN (Commercial-domestic)",
    "sku": "1690728",
    "quantity": 834,
    "price": 425
  },
  {
    "name": "EGG PAN 16CM PINK & BLUE",
    "brand": "KITCHEN (Commercial-domestic)",
    "sku": "1690729",
    "quantity": 570,
    "price": 525
  },
  {
    "name": "EGG SLICER",
    "brand": "KITCHEN (Commercial-domestic)",
    "sku": "11431",
    "quantity": 215,
    "price": 65
  },
  {
    "name": "FOOD TONG BLACK",
    "brand": "KITCHEN (Commercial-domestic)",
    "sku": "T12",
    "quantity": 274,
    "price": 80
  },
  {
    "name": "GLASS STAND 19*19*24",
    "brand": "KITCHEN (Commercial-domestic)",
    "sku": "A08180D",
    "quantity": 372,
    "price": 315
  },
  {
    "name": "GLASS STAND 22*13.5*24",
    "brand": "KITCHEN (Commercial-domestic)",
    "sku": "A08179D",
    "quantity": 382,
    "price": 315
  },
  {
    "name": "ICE MOULD",
    "brand": "KITCHEN (Commercial-domestic)",
    "sku": "180411",
    "quantity": 701,
    "price": 115
  },
  {
    "name": "ICE MOULD",
    "brand": "KITCHEN (Commercial-domestic)",
    "sku": "AJW7978",
    "quantity": 384,
    "price": 95
  },
  {
    "name": "RICE SPOON 9.3X25.3CM",
    "brand": "KITCHEN (Commercial-domestic)",
    "sku": "192091",
    "quantity": 526,
    "price": 98
  },
  {
    "name": "SAUCE BOTTLE YELLOW & RED 2 PCS SET",
    "brand": "KITCHEN (Commercial-domestic)",
    "sku": "102SB",
    "quantity": 498,
    "price": 135
  },
  {
    "name": "SILICON STOPPER CHAMPAGNE S/S",
    "brand": "KITCHEN (Commercial-domestic)",
    "sku": "BLH721",
    "quantity": 212,
    "price": 250
  },
  {
    "name": "SPADE W/WOOD HANDLE",
    "brand": "KITCHEN (Commercial-domestic)",
    "sku": "005#",
    "quantity": 210,
    "price": 245
  },
  {
    "name": "TONG. 12.0\"",
    "brand": "KITCHEN (Commercial-domestic)",
    "sku": "12T",
    "quantity": 668,
    "price": 100
  },
  {
    "name": "TONG. 14.0\"",
    "brand": "KITCHEN (Commercial-domestic)",
    "sku": "14T",
    "quantity": 717,
    "price": 110
  },
  {
    "name": "TONG. 9.0\"",
    "brand": "KITCHEN (Commercial-domestic)",
    "sku": "9T",
    "quantity": 230,
    "price": 80
  },
  {
    "name": "TRAY DIVIDED RECT. FOR FOOD (40X30)CM",
    "brand": "KITCHEN (Commercial-domestic)",
    "sku": "4030P",
    "quantity": 239,
    "price": 645
  },
  {
    "name": "TRAY FAST FOOD RED (42.5X30X3.5)",
    "brand": "KITCHEN (Commercial-domestic)",
    "sku": "818FF",
    "quantity": 378,
    "price": 245
  },
  {
    "name": "TRAY FIBER NON-SLIP BROWN (20X15)\" RECT.",
    "brand": "KITCHEN (Commercial-domestic)",
    "sku": "1520CTUSA",
    "quantity": 443,
    "price": 1495
  },
  {
    "name": "TRAY FIBER NON-SLIP BROWN 18.0\" ROUND",
    "brand": "KITCHEN (Commercial-domestic)",
    "sku": "1800CTUSA",
    "quantity": 369,
    "price": 995
  }

]